CHANGES.txt
LICENSE
MANIFEST.in
README.md
requirements.txt
setup.py
django_pg_current_timestamp/__init__.py
django_pg_current_timestamp/models.py
django_pg_current_timestamp.egg-info/PKG-INFO
django_pg_current_timestamp.egg-info/SOURCES.txt
django_pg_current_timestamp.egg-info/dependency_links.txt
django_pg_current_timestamp.egg-info/not-zip-safe
django_pg_current_timestamp.egg-info/requires.txt
django_pg_current_timestamp.egg-info/top_level.txt
django_pg_current_timestamp/django_pg_current_timestamp_test_app/__init__.py
django_pg_current_timestamp/django_pg_current_timestamp_test_app/models.py
django_pg_current_timestamp/tests/CurrentTimestampTest.py
django_pg_current_timestamp/tests/__init__.py