Metadata-Version: 1.1
Name: django-pg-current-timestamp
Version: 0.2.3
Summary: Add true postgresql `CURRENT_TIMESTAMP` support to Django + PostgreSQL
Home-page: https://github.com/threatstream/django-pg-current-timestamp
Author: Jay Taylor
Author-email: jay@jaytaylor.com
License: Copyright (c) 2014 by ThreatStream, Inc. All rights reserved.
